toymeta/__init__.py
toymeta/dark_key_door.py
toymeta/dark_room.py
toymeta-0.0.1.dist-info/LICENSE
toymeta-0.0.1.dist-info/METADATA
toymeta-0.0.1.dist-info/WHEEL
toymeta-0.0.1.dist-info/top_level.txt
toymeta-0.0.1.dist-info/RECORD
