Metadata-Version: 2.1
Name: toymeta
Version: 0.0.1
Summary: Toy meta-reinforcement learning environments to test algorithms implementations
Author-email: Alexander Nikulin <a.p.nikulin@tinkoff.ai>
License: Apache License
Keywords: reinforcement learning,meta-reinforcement learning,gridworld,dark room
Classifier: Development Status :: 4 - Beta
Classifier: Intended Audience :: Developers
Classifier: Intended Audience :: Science/Research
Classifier: Natural Language :: English
Classifier: Programming Language :: Python
Classifier: Programming Language :: Python :: 3
Classifier: Programming Language :: Python :: 3.9
Classifier: Programming Language :: Python :: 3.10
Classifier: Topic :: Scientific/Engineering :: Artificial Intelligence
Classifier: License :: OSI Approved :: Apache Software License
Requires-Python: >=3.9
License-File: LICENSE
Requires-Dist: gymnasium >=0.29.0
Provides-Extra: dev
Requires-Dist: ruff >=0.1.6 ; extra == 'dev'
Requires-Dist: pre-commit >=3.3.3 ; extra == 'dev'
Requires-Dist: pyright >=1.1.347 ; extra == 'dev'
